tei/__init__.py
tei/client.py
teicli-0.3.3.dist-info/METADATA
teicli-0.3.3.dist-info/WHEEL
teicli-0.3.3.dist-info/RECORD
