Metadata-Version: 2.1
Name: teicli
Version: 0.3.3
Summary: Text Embeddings Inference (TEI)'s unofficial python wrapper library for batch processing with asyncio
Author-email: seonglae <sungle3737@gmail.com>
Requires-Python: >=3.8.0
Requires-Dist: aiohttp>=3.8.6
Requires-Dist: requests>=2.31.0
